README.md
pyproject.toml
guardfive/__init__.py
guardfive/cli.py
guardfive/models.py
guardfive/scanner.py
guardfive.egg-info/PKG-INFO
guardfive.egg-info/SOURCES.txt
guardfive.egg-info/dependency_links.txt
guardfive.egg-info/entry_points.txt
guardfive.egg-info/requires.txt
guardfive.egg-info/top_level.txt
guardfive/connectors/__init__.py
guardfive/connectors/mcp_client.py
guardfive/connectors/remote.py
guardfive/detectors/__init__.py
guardfive/detectors/command_injection.py
guardfive/detectors/rug_pull.py
guardfive/detectors/secrets_exposure.py
guardfive/detectors/shadowing.py
guardfive/detectors/ssrf.py
guardfive/detectors/tool_poisoning.py
tests/__init__.py
tests/test_detectors.py
venv/Lib/site-packages/__editable___guardfive_0_1_0_finder.py
venv/Lib/site-packages/pythoncom.py
venv/Lib/site-packages/typing_extensions.py
venv/Lib/site-packages/adodbapi/__init__.py
venv/Lib/site-packages/adodbapi/ado_consts.py
venv/Lib/site-packages/adodbapi/adodbapi.py
venv/Lib/site-packages/adodbapi/apibase.py
venv/Lib/site-packages/adodbapi/is64bit.py
venv/Lib/site-packages/adodbapi/process_connect_string.py
venv/Lib/site-packages/adodbapi/schema_table.py
venv/Lib/site-packages/adodbapi/setup.py
venv/Lib/site-packages/adodbapi/examples/db_print.py
venv/Lib/site-packages/adodbapi/examples/db_table_names.py
venv/Lib/site-packages/adodbapi/examples/xls_read.py
venv/Lib/site-packages/adodbapi/examples/xls_write.py
venv/Lib/site-packages/adodbapi/test/adodbapitest.py
venv/Lib/site-packages/adodbapi/test/adodbapitestconfig.py
venv/Lib/site-packages/adodbapi/test/dbapi20.py
venv/Lib/site-packages/adodbapi/test/is64bit.py
venv/Lib/site-packages/adodbapi/test/setuptestframework.py
venv/Lib/site-packages/adodbapi/test/test_adodbapi_dbapi20.py
venv/Lib/site-packages/adodbapi/test/tryconnection.py
venv/Lib/site-packages/annotated_types/__init__.py
venv/Lib/site-packages/annotated_types/py.typed
venv/Lib/site-packages/annotated_types/test_cases.py
venv/Lib/site-packages/anyio/__init__.py
venv/Lib/site-packages/anyio/from_thread.py
venv/Lib/site-packages/anyio/functools.py
venv/Lib/site-packages/anyio/lowlevel.py
venv/Lib/site-packages/anyio/py.typed
